src/tests/__init__.py
src/tests/test_base.py
src/tests/components/__init__.py
src/tests/components/test_blockquote.py
src/tests/components/test_button.py
src/tests/components/test_checkbox.py
src/tests/components/test_code.py
src/tests/components/test_divider.py
src/tests/components/test_form.py
src/tests/components/test_heading.py
src/tests/components/test_image.py
src/tests/components/test_input.py
src/tests/components/test_label.py
src/tests/components/test_link.py
src/tests/components/test_list.py
src/tests/components/test_paragraph.py
src/tests/components/test_preformatted.py
src/tests/components/test_radio.py
src/tests/components/test_select.py
src/tests/components/test_slider.py
src/tests/components/test_table.py
src/tests/components/test_textarea.py
src/trunco/html/__init__.py
src/trunco/html/base.py
src/trunco/html/enums.py
src/trunco/html/components/__init__.py
src/trunco/html/components/blockquote.py
src/trunco/html/components/button.py
src/trunco/html/components/checkbox.py
src/trunco/html/components/code.py
src/trunco/html/components/divider.py
src/trunco/html/components/form.py
src/trunco/html/components/heading.py
src/trunco/html/components/image.py
src/trunco/html/components/input.py
src/trunco/html/components/label.py
src/trunco/html/components/link.py
src/trunco/html/components/list.py
src/trunco/html/components/paragraph.py
src/trunco/html/components/preformattedText.py
src/trunco/html/components/radio.py
src/trunco/html/components/select.py
src/trunco/html/components/slider.py
src/trunco/html/components/table.py
src/trunco/html/components/textarea.py
trunco_core-0.1.1.dist-info/METADATA
trunco_core-0.1.1.dist-info/WHEEL
trunco_core-0.1.1.dist-info/RECORD
