Metadata-Version: 2.4
Name: trunco-core
Version: 0.1.1
Summary: core modules for trunco package
Author-email: Ali Tavallaie <a.tavallaie@gmail.com>
License-Expression: MIT
Requires-Python: >=3.8
